AUTHORS.rst
CONTRIBUTING.rst
HISTORY.rst
LICENSE
MANIFEST.in
README.rst
setup.cfg
setup.py
majesticseo/__init__.py
majesticseo/items.py
majesticseo/majestic.py
majesticseo.egg-info/PKG-INFO
majesticseo.egg-info/SOURCES.txt
majesticseo.egg-info/dependency_links.txt
majesticseo.egg-info/not-zip-safe
majesticseo.egg-info/requires.txt
majesticseo.egg-info/top_level.txt