Metadata-Version: 1.1
Name: majesticseo
Version: 0.0.2
Summary: Python Wrapper around the MajesticSEO API
Home-page: https://github.com/philippe2803/majesticseo
Author: Philippe Oger
Author-email: phil.oger@gmail.com
License: MIT license
Keywords: majesticseo
Platform: UNKNOWN
Classifier: Development Status :: 2 - Pre-Alpha
Classifier: Intended Audience :: Developers
Classifier: License :: OSI Approved :: MIT License
Classifier: Natural Language :: English
Classifier: Programming Language :: Python :: 2.6
Classifier: Programming Language :: Python :: 2.7
Classifier: Programming Language :: Python :: 3
Classifier: Programming Language :: Python :: 3.3
Classifier: Programming Language :: Python :: 3.4
Classifier: Programming Language :: Python :: 3.5
